{
"moduleCode": "SE3216",
"moduleTitle": "Migration and Diaspora in Southeast Asia",
"moduleCredit": "4",
"lockedModules":[
],
"preclusion": "NIL",
"prerequisite" : "NIL",
"preclusionList": [],
"parsedPrerequisite" : "nil",
"prerequisiteList": [],
"completePrerequisite": {
            "name": "SE3216", 
            "children": []
},
"moduleDescription": "The module focuses on migrants in Southeast Asian countries from the historical-anthropological perspectives. Discussions include the concepts and patterns of migration in the region, the factors that give rise to migrations, for example, economic hardship and poverty, ethnic conflict, colonialism, political independence and the formation of modern nation-states, and the impact on both the home and host countries.",
"crossModule": "-1",
"corequisite": "-1",
"faculty": "ARTS & SOCIAL SCIENCES",
"department": "SOUTHEAST ASIAN STUDIES",
"history": [[0,0,0,0,0],[0,0,0,0,0],[2013,0,2,0,0],[0,0,0,0,0],[0,0,0,0,0],[2016,1,0,0,0]]
}
