{
"name":"Bachelor of Science (Statistics)",
"faculty":"SCIENCE",
"type":"degree programme,",
"AY":2012,
"updated":"20/7/2016",
"link":"http://www.stat.nus.edu.sg/opencms/currentstudents/prog_ugradstruct_FOS.html#BSc2007",
"FLR": {"ownBasket":["CZ","ST","QF","DSA"],"others":[["CZ","CS","IT1001","IT1002","IT1006","QF","ZB"],["CM","FST","PR"],["FST","LSM","PR"],["PC"],["SP1201","FSM12","SP1202","SP1203","SP2251","S3201","SP3202","SP3203","SP3277","SP1541"]]}, 
"restriction": {},
"mainList":[{"listName":"Level 1000","requirement":4,"list":{"and":[{"or":[{"code":"ST1131","rank":3,"flag":false},{"code":"ST1232","rank":3,"flag":false}],"id":"L1_sub1","fulfilled" :false},{"code":"MA1101R","rank":1,"flag":false},{"code":"MA1102R","rank":1,"flag":false},{"or":[{"code":"CS1010","rank":3,"flag":false},{"code":"CS1010E","rank":3,"flag":false},{"code":"CS1010S","rank":3,"flag":false},{"code":"CS1010FC","rank":3,"flag":false}],"id":"L1_sub2","fulfilled" :false}],"fulfilled":false}},{"listName":"Level 2000","requirement":4,"list":{"and":[{"or":[{"code":"MA2311","rank":3,"flag":false},{"code":"MA2108","rank":3,"flag":false},{"code":"MA2108S","rank":3,"flag":false}],"id":"L2_sub1","fulfilled" :false},{"code":"ST2132","rank":1,"flag":false},{"code":"ST2137","rank":1,"flag":false},{"or":[{"code":"ST2131","rank":3,"flag":false},{"code":"MA2216","rank":3,"flag":false}],"id":"L2_sub2","fulfilled" :false}],"fulfilled":false}},{"listName":"Level 3000","requirement":7,"list":{"and":[{"code":"ST3131","rank":1,"flag":false},{"or":[{"code":"MA3236","rank":3,"flag":false},{"code":"MA3238","rank":3,"flag":false}],"id":"L3_sub1","fulfilled" :false},{"code":"ST3241","rank":1,"flag":false},{"or":[{"code":"ST3232","rank":4,"flag":false},{"code":"ST3233","rank":4,"flag":false},{"code":"ST3236","rank":4,"flag":false},{"code":"ST3239","rank":4,"flag":false},{"code":"ST3240","rank":4,"flag":false},{"code":"ST3241","rank":4,"flag":false},{"code":"ST3243","rank":4,"flag":false},{"code":"ST3246","rank":4,"flag":false},{"code":"ST3247","rank":4,"flag":false},{"code":"ST3288","rank":4,"flag":false},{"code":"ST3289","rank":4,"flag":false},{"code":"ST4199","rank":4,"flag":false},{"code":"ST4231","rank":4,"flag":false},{"code":"ST4232","rank":4,"flag":false},{"code":"ST4233","rank":4,"flag":false},{"code":"ST4234","rank":4,"flag":false},{"code":"ST4238","rank":4,"flag":false},{"code":"ST4240","rank":4,"flag":false},{"code":"ST4241","rank":4,"flag":false},{"code":"ST4242","rank":4,"flag":false},{"code":"ST4245","rank":4,"flag":false},{"code":"ST4991","rank":4,"flag":false},{"code":"ST4992","rank":4,"flag":false}],"id":"L3_sub2","fulfilled" :false},{"or":[{"code":"ST3232","rank":4,"flag":false},{"code":"ST3233","rank":4,"flag":false},{"code":"ST3236","rank":4,"flag":false},{"code":"ST3239","rank":4,"flag":false},{"code":"ST3240","rank":4,"flag":false},{"code":"ST3241","rank":4,"flag":false},{"code":"ST3243","rank":4,"flag":false},{"code":"ST3246","rank":4,"flag":false},{"code":"ST3247","rank":4,"flag":false},{"code":"ST3288","rank":4,"flag":false},{"code":"ST3289","rank":4,"flag":false},{"code":"ST4199","rank":4,"flag":false},{"code":"ST4231","rank":4,"flag":false},{"code":"ST4232","rank":4,"flag":false},{"code":"ST4233","rank":4,"flag":false},{"code":"ST4234","rank":4,"flag":false},{"code":"ST4238","rank":4,"flag":false},{"code":"ST4240","rank":4,"flag":false},{"code":"ST4241","rank":4,"flag":false},{"code":"ST4242","rank":4,"flag":false},{"code":"ST4245","rank":4,"flag":false},{"code":"ST4991","rank":4,"flag":false},{"code":"ST4992","rank":4,"flag":false}],"id":"L3_sub2","fulfilled" :false},{"or":[{"code":"ST3232","rank":4,"flag":false},{"code":"ST3233","rank":4,"flag":false},{"code":"ST3236","rank":4,"flag":false},{"code":"ST3239","rank":4,"flag":false},{"code":"ST3240","rank":4,"flag":false},{"code":"ST3241","rank":4,"flag":false},{"code":"ST3243","rank":4,"flag":false},{"code":"ST3246","rank":4,"flag":false},{"code":"ST3247","rank":4,"flag":false},{"code":"ST3288","rank":4,"flag":false},{"code":"ST3289","rank":4,"flag":false},{"code":"ST4199","rank":4,"flag":false},{"code":"ST4231","rank":4,"flag":false},{"code":"ST4232","rank":4,"flag":false},{"code":"ST4233","rank":4,"flag":false},{"code":"ST4234","rank":4,"flag":false},{"code":"ST4238","rank":4,"flag":false},{"code":"ST4240","rank":4,"flag":false},{"code":"ST4241","rank":4,"flag":false},{"code":"ST4242","rank":4,"flag":false},{"code":"ST4245","rank":4,"flag":false},{"code":"ST4991","rank":4,"flag":false},{"code":"ST4992","rank":4,"flag":false},{"or":[{"code":"MA3209","rank":3,"flag":false},{"code":"MA3218","rank":3,"flag":false},{"code":"MA3227","rank":3,"flag":false},{"code":"MA3229","rank":3,"flag":false},{"code":"MA3233","rank":3,"flag":false},{"code":"MA3236","rank":3,"flag":false},{"code":"MA3245","rank":3,"flag":false},{"code":"MA3252","rank":3,"flag":false},{"code":"MA3256","rank":3,"flag":false},{"code":"MA3259","rank":3,"flag":false},{"code":"QF3101","rank":3,"flag":false},{"code":"CS3230","rank":3,"flag":false},{"code":"CS3223","rank":3,"flag":false},{"code":"CS3233","rank":3,"flag":false},{"code":"CS3243","rank":3,"flag":false},{"code":"CS3244","rank":3,"flag":false},{"code":"CS3304","rank":3,"flag":false}],"id":"listA","fulfilled" :false},{"or":[{"code":"MA4211","rank":3,"flag":false},{"code":"MA4229","rank":3,"flag":false},{"code":"MA4230","rank":3,"flag":false},{"code":"MA4233","rank":3,"flag":false},{"code":"MA4254","rank":3,"flag":false},{"code":"MA4257","rank":3,"flag":false},{"code":"MA4260","rank":3,"flag":false},{"code":"MA4261","rank":3,"flag":false},{"code":"MA4262","rank":3,"flag":false},{"code":"CS4231","rank":3,"flag":false},{"code":"CS4220","rank":3,"flag":false},{"code":"EC4303","rank":3,"flag":false}],"id":"listB","fulfilled" :false}],"id":"L3_sub3","fulfilled" :false},{"or":[{"code":"ST3232","rank":4,"flag":false},{"code":"ST3233","rank":4,"flag":false},{"code":"ST3236","rank":4,"flag":false},{"code":"ST3239","rank":4,"flag":false},{"code":"ST3240","rank":4,"flag":false},{"code":"ST3241","rank":4,"flag":false},{"code":"ST3243","rank":4,"flag":false},{"code":"ST3246","rank":4,"flag":false},{"code":"ST3247","rank":4,"flag":false},{"code":"ST3288","rank":4,"flag":false},{"code":"ST3289","rank":4,"flag":false},{"code":"ST4199","rank":4,"flag":false},{"code":"ST4231","rank":4,"flag":false},{"code":"ST4232","rank":4,"flag":false},{"code":"ST4233","rank":4,"flag":false},{"code":"ST4234","rank":4,"flag":false},{"code":"ST4238","rank":4,"flag":false},{"code":"ST4240","rank":4,"flag":false},{"code":"ST4241","rank":4,"flag":false},{"code":"ST4242","rank":4,"flag":false},{"code":"ST4245","rank":4,"flag":false},{"code":"ST4991","rank":4,"flag":false},{"code":"ST4992","rank":4,"flag":false},{"or":[{"code":"MA3209","rank":3,"flag":false},{"code":"MA3218","rank":3,"flag":false},{"code":"MA3227","rank":3,"flag":false},{"code":"MA3229","rank":3,"flag":false},{"code":"MA3233","rank":3,"flag":false},{"code":"MA3236","rank":3,"flag":false},{"code":"MA3245","rank":3,"flag":false},{"code":"MA3252","rank":3,"flag":false},{"code":"MA3256","rank":3,"flag":false},{"code":"MA3259","rank":3,"flag":false},{"code":"QF3101","rank":3,"flag":false},{"code":"CS3230","rank":3,"flag":false},{"code":"CS3223","rank":3,"flag":false},{"code":"CS3233","rank":3,"flag":false},{"code":"CS3243","rank":3,"flag":false},{"code":"CS3244","rank":3,"flag":false},{"code":"CS3304","rank":3,"flag":false}],"id":"listA","fulfilled" :false},{"or":[{"code":"MA4211","rank":3,"flag":false},{"code":"MA4229","rank":3,"flag":false},{"code":"MA4230","rank":3,"flag":false},{"code":"MA4233","rank":3,"flag":false},{"code":"MA4254","rank":3,"flag":false},{"code":"MA4257","rank":3,"flag":false},{"code":"MA4260","rank":3,"flag":false},{"code":"MA4261","rank":3,"flag":false},{"code":"MA4262","rank":3,"flag":false},{"code":"CS4231","rank":3,"flag":false},{"code":"CS4220","rank":3,"flag":false},{"code":"EC4303","rank":3,"flag":false}],"id":"listB","fulfilled" :false}],"id":"L3_sub3","fulfilled" :false}],"fulfilled":false}},{"listName":"Level 4000","requirement":7,"list":{"and":[{"code":"ST4199","rank":1,"flag":false},{"code":"ST4199","rank":4,"flag":false},{"code":"ST4231","rank":4,"flag":false},{"code":"ST4232","rank":4,"flag":false},{"code":"ST4233","rank":4,"flag":false},{"code":"ST4234","rank":4,"flag":false},{"code":"ST4238","rank":4,"flag":false},{"code":"ST4240","rank":4,"flag":false},{"code":"ST4241","rank":4,"flag":false},{"code":"ST4242","rank":4,"flag":false},{"code":"ST4245","rank":4,"flag":false},{"code":"ST4991","rank":4,"flag":false},{"code":"ST4992","rank":4,"flag":false},{"code":"ST4199","rank":4,"flag":false},{"code":"ST4231","rank":4,"flag":false},{"code":"ST4232","rank":4,"flag":false},{"code":"ST4233","rank":4,"flag":false},{"code":"ST4234","rank":4,"flag":false},{"code":"ST4238","rank":4,"flag":false},{"code":"ST4240","rank":4,"flag":false},{"code":"ST4241","rank":4,"flag":false},{"code":"ST4242","rank":4,"flag":false},{"code":"ST4245","rank":4,"flag":false},{"code":"ST4991","rank":4,"flag":false},{"code":"ST4992","rank":4,"flag":false},{"code":"ST4199","rank":4,"flag":false},{"code":"ST4231","rank":4,"flag":false},{"code":"ST4232","rank":4,"flag":false},{"code":"ST4233","rank":4,"flag":false},{"code":"ST4234","rank":4,"flag":false},{"code":"ST4238","rank":4,"flag":false},{"code":"ST4240","rank":4,"flag":false},{"code":"ST4241","rank":4,"flag":false},{"code":"ST4242","rank":4,"flag":false},{"code":"ST4245","rank":4,"flag":false},{"code":"ST4991","rank":4,"flag":false},{"code":"ST4992","rank":4,"flag":false},{"code":"ST4199","rank":4,"flag":false},{"code":"ST4231","rank":4,"flag":false},{"code":"ST4232","rank":4,"flag":false},{"code":"ST4233","rank":4,"flag":false},{"code":"ST4234","rank":4,"flag":false},{"code":"ST4238","rank":4,"flag":false},{"code":"ST4240","rank":4,"flag":false},{"code":"ST4241","rank":4,"flag":false},{"code":"ST4242","rank":4,"flag":false},{"code":"ST4245","rank":4,"flag":false},{"code":"ST4991","rank":4,"flag":false},{"code":"ST4992","rank":4,"flag":false},{"or":[{"code":"ST4199","rank":4,"flag":false},{"code":"ST4231","rank":4,"flag":false},{"code":"ST4232","rank":4,"flag":false},{"code":"ST4233","rank":4,"flag":false},{"code":"ST4234","rank":4,"flag":false},{"code":"ST4238","rank":4,"flag":false},{"code":"ST4240","rank":4,"flag":false},{"code":"ST4241","rank":4,"flag":false},{"code":"ST4242","rank":4,"flag":false},{"code":"ST4245","rank":4,"flag":false},{"code":"ST4991","rank":4,"flag":false},{"code":"ST4992","rank":4,"flag":false},{"code":"ST5198","rank":4,"flag":false},{"code":"ST5199","rank":4,"flag":false},{"code":"ST5201","rank":4,"flag":false},{"code":"ST5202","rank":4,"flag":false},{"code":"ST5203","rank":4,"flag":false},{"code":"ST5207","rank":4,"flag":false},{"code":"ST5208","rank":4,"flag":false},{"code":"ST5209","rank":4,"flag":false},{"code":"ST5211","rank":4,"flag":false},{"code":"ST5214","rank":4,"flag":false},{"code":"ST5215","rank":4,"flag":false},{"code":"ST5222","rank":4,"flag":false},{"code":"ST5223","rank":4,"flag":false},{"code":"ST5224","rank":4,"flag":false},{"code":"ST5225","rank":4,"flag":false},{"code":"ST5241A","rank":4,"flag":false},{"or":[{"code":"MA4211","rank":3,"flag":false},{"code":"MA4229","rank":3,"flag":false},{"code":"MA4230","rank":3,"flag":false},{"code":"MA4233","rank":3,"flag":false},{"code":"MA4254","rank":3,"flag":false},{"code":"MA4257","rank":3,"flag":false},{"code":"MA4260","rank":3,"flag":false},{"code":"MA4261","rank":3,"flag":false},{"code":"MA4262","rank":3,"flag":false},{"code":"CS4231","rank":3,"flag":false},{"code":"CS4220","rank":3,"flag":false},{"code":"EC4303","rank":3,"flag":false}],"id":"listB","fulfilled" :false}],"id":"L4_sub1","fulfilled" :false},{"or":[{"code":"ST4199","rank":4,"flag":false},{"code":"ST4231","rank":4,"flag":false},{"code":"ST4232","rank":4,"flag":false},{"code":"ST4233","rank":4,"flag":false},{"code":"ST4234","rank":4,"flag":false},{"code":"ST4238","rank":4,"flag":false},{"code":"ST4240","rank":4,"flag":false},{"code":"ST4241","rank":4,"flag":false},{"code":"ST4242","rank":4,"flag":false},{"code":"ST4245","rank":4,"flag":false},{"code":"ST4991","rank":4,"flag":false},{"code":"ST4992","rank":4,"flag":false},{"code":"ST5198","rank":4,"flag":false},{"code":"ST5199","rank":4,"flag":false},{"code":"ST5201","rank":4,"flag":false},{"code":"ST5202","rank":4,"flag":false},{"code":"ST5203","rank":4,"flag":false},{"code":"ST5207","rank":4,"flag":false},{"code":"ST5208","rank":4,"flag":false},{"code":"ST5209","rank":4,"flag":false},{"code":"ST5211","rank":4,"flag":false},{"code":"ST5214","rank":4,"flag":false},{"code":"ST5215","rank":4,"flag":false},{"code":"ST5222","rank":4,"flag":false},{"code":"ST5223","rank":4,"flag":false},{"code":"ST5224","rank":4,"flag":false},{"code":"ST5225","rank":4,"flag":false},{"code":"ST5241A","rank":4,"flag":false},{"or":[{"code":"MA4211","rank":3,"flag":false},{"code":"MA4229","rank":3,"flag":false},{"code":"MA4230","rank":3,"flag":false},{"code":"MA4233","rank":3,"flag":false},{"code":"MA4254","rank":3,"flag":false},{"code":"MA4257","rank":3,"flag":false},{"code":"MA4260","rank":3,"flag":false},{"code":"MA4261","rank":3,"flag":false},{"code":"MA4262","rank":3,"flag":false},{"code":"CS4231","rank":3,"flag":false},{"code":"CS4220","rank":3,"flag":false},{"code":"EC4303","rank":3,"flag":false}],"id":"listB","fulfilled" :false}],"id":"L4_sub1","fulfilled" :false}],"fulfilled":false}}],"visibleLists":["Level 1000","Level 2000","Level 3000","Level 4000"],
"specialisations":
[{"name":"Biostatistics","listName":"biostatistics","requirement":6,"list":{"and":[{"code":"ST3232","rank":2,"flag":false},{"code":"ST3242","rank":2,"flag":false},{"code":"ST3243","rank":2,"flag":false},{"code":"ST3245","rank":2,"flag":false},{"code":"MA3259","rank":2,"flag":false},{"code":"ST4232","rank":2,"flag":false},{"code":"ST4241","rank":2,"flag":false},{"code":"ST4242","rank":2,"flag":false},{"code":"ST4243","rank":2,"flag":false}],"fulfilled":false}}
,{"name":"Finance and Business statistics","listName":"FBS","requirement":6,"list":{"and":[{"or":[{"code":"ST3233","rank":3,"flag":false},{"code":"ST3234","rank":3,"flag":false},{"code":"ST3246","rank":3,"flag":false},{"code":"MA3245","rank":3,"flag":false},{"code":"ST4245","rank":3,"flag":false},{"code":"MA4257","rank":3,"flag":false}],"id":"fbs1","fulfilled" :false},{"or":[{"code":"ST3233","rank":3,"flag":false},{"code":"ST3234","rank":3,"flag":false},{"code":"ST3246","rank":3,"flag":false},{"code":"MA3245","rank":3,"flag":false},{"code":"ST4245","rank":3,"flag":false},{"code":"MA4257","rank":3,"flag":false}],"id":"fbs1","fulfilled" :false},{"or":[{"code":"ST3239","rank":3,"flag":false},{"code":"ST3240","rank":3,"flag":false},{"code":"ST4233","rank":3,"flag":false},{"code":"ST4238","rank":3,"flag":false},{"code":"ST4240","rank":3,"flag":false}],"id":"fbs2","fulfilled" :false},{"or":[{"code":"ST3239","rank":3,"flag":false},{"code":"ST3240","rank":3,"flag":false},{"code":"ST4233","rank":3,"flag":false},{"code":"ST4238","rank":3,"flag":false},{"code":"ST4240","rank":3,"flag":false}],"id":"fbs2","fulfilled" :false},{"or":[{"or":[{"code":"ST3233","rank":3,"flag":false},{"code":"ST3234","rank":3,"flag":false},{"code":"ST3246","rank":3,"flag":false},{"code":"MA3245","rank":3,"flag":false},{"code":"ST4245","rank":3,"flag":false},{"code":"MA4257","rank":3,"flag":false}],"id":"fbs1","fulfilled" :false},{"or":[{"code":"ST3239","rank":3,"flag":false},{"code":"ST3240","rank":3,"flag":false},{"code":"ST4233","rank":3,"flag":false},{"code":"ST4238","rank":3,"flag":false},{"code":"ST4240","rank":3,"flag":false}],"id":"fbs2","fulfilled" :false}],"id":"fbs3","fulfilled" :false},{"or":[{"or":[{"code":"ST3233","rank":3,"flag":false},{"code":"ST3234","rank":3,"flag":false},{"code":"ST3246","rank":3,"flag":false},{"code":"MA3245","rank":3,"flag":false},{"code":"ST4245","rank":3,"flag":false},{"code":"MA4257","rank":3,"flag":false}],"id":"fbs1","fulfilled" :false},{"or":[{"code":"ST3239","rank":3,"flag":false},{"code":"ST3240","rank":3,"flag":false},{"code":"ST4233","rank":3,"flag":false},{"code":"ST4238","rank":3,"flag":false},{"code":"ST4240","rank":3,"flag":false}],"id":"fbs2","fulfilled" :false}],"id":"fbs3","fulfilled" :false}],"fulfilled":false}}
]
}
